PYR.py
HelpPython-0.0.0.0.1.dist-info/METADATA
HelpPython-0.0.0.0.1.dist-info/WHEEL
HelpPython-0.0.0.0.1.dist-info/top_level.txt
HelpPython-0.0.0.0.1.dist-info/RECORD
