Metadata-Version: 2.1
Name: HelpPython
Version: 0.0.0.0.1
Summary: 模块
Author: sunruiyang
Author-email: dogsmallsmile@163.com
